km3services/__init__.py
km3services/_tools.py
km3services/core.py
km3services/oscprob.py
km3services-0.4.2.dist-info/LICENSE
km3services-0.4.2.dist-info/METADATA
km3services-0.4.2.dist-info/WHEEL
km3services-0.4.2.dist-info/top_level.txt
km3services-0.4.2.dist-info/RECORD
